[
  {
    "origin_country_norm": "Panama",
    "origin_country_cn": "巴拿马",
    "origin_display_cn": "巴拿马",
    "lat": 8.538,
    "lon": -80.7821,
    "sample_size": 70,
    "avg_rating": 94.5,
    "median_rating": 95.0,
    "median_price_100g_usd": 23.0,
    "count_94plus": 60,
    "share_94plus": 0.8571,
    "count_95plus": 36,
    "share_95plus": 0.5143,
    "rating_band": "93.50-94.50",
    "rating_band_order": 4,
    "map_note": "Plot at country centroid",
    "label_priority": 1
  },
  {
    "origin_country_norm": "Kenya",
    "origin_country_cn": "肯尼亚",
    "origin_display_cn": "肯尼亚",
    "lat": -0.0236,
    "lon": 37.9062,
    "sample_size": 143,
    "avg_rating": 93.87,
    "median_rating": 94.0,
    "median_price_100g_usd": 6.23,
    "count_94plus": 93,
    "share_94plus": 0.6503,
    "count_95plus": 39,
    "share_95plus": 0.2727,
    "rating_band": "93.50-94.50",
    "rating_band_order": 4,
    "map_note": "Plot at country centroid",
    "label_priority": 1
  },
  {
    "origin_country_norm": "Yemen",
    "origin_country_cn": "也门",
    "origin_display_cn": "也门",
    "lat": 15.5527,
    "lon": 48.5164,
    "sample_size": 13,
    "avg_rating": 93.62,
    "median_rating": 93.0,
    "median_price_100g_usd": 15.43,
    "count_94plus": 6,
    "share_94plus": 0.4615,
    "count_95plus": 2,
    "share_95plus": 0.1538,
    "rating_band": "93.50-94.50",
    "rating_band_order": 4,
    "map_note": "Plot at country centroid",
    "label_priority": 1
  },
  {
    "origin_country_norm": "Ethiopia",
    "origin_country_cn": "埃塞俄比亚",
    "origin_display_cn": "埃塞俄比亚",
    "lat": 9.145,
    "lon": 40.4897,
    "sample_size": 447,
    "avg_rating": 93.45,
    "median_rating": 93.0,
    "median_price_100g_usd": 5.58,
    "count_94plus": 222,
    "share_94plus": 0.4966,
    "count_95plus": 87,
    "share_95plus": 0.1946,
    "rating_band": "93.00-93.49",
    "rating_band_order": 3,
    "map_note": "Plot at country centroid",
    "label_priority": 1
  },
  {
    "origin_country_norm": "United States",
    "origin_country_cn": "美国",
    "origin_display_cn": "美国夏威夷",
    "lat": 19.6426,
    "lon": -155.9969,
    "sample_size": 113,
    "avg_rating": 93.45,
    "median_rating": 94.0,
    "median_price_100g_usd": 17.64,
    "count_94plus": 61,
    "share_94plus": 0.5398,
    "count_95plus": 28,
    "share_95plus": 0.2478,
    "rating_band": "93.00-93.49",
    "rating_band_order": 3,
    "map_note": "Plot at Hawaii origin",
    "label_priority": 1
  },
  {
    "origin_country_norm": "Colombia",
    "origin_country_cn": "哥伦比亚",
    "origin_display_cn": "哥伦比亚",
    "lat": 4.5709,
    "lon": -74.2973,
    "sample_size": 150,
    "avg_rating": 93.17,
    "median_rating": 93.0,
    "median_price_100g_usd": 7.35,
    "count_94plus": 71,
    "share_94plus": 0.4733,
    "count_95plus": 23,
    "share_95plus": 0.1533,
    "rating_band": "93.00-93.49",
    "rating_band_order": 3,
    "map_note": "Plot at country centroid",
    "label_priority": 1
  },
  {
    "origin_country_norm": "Nicaragua",
    "origin_country_cn": "尼加拉瓜",
    "origin_display_cn": "尼加拉瓜",
    "lat": 12.8654,
    "lon": -85.2072,
    "sample_size": 11,
    "avg_rating": 93.09,
    "median_rating": 93.0,
    "median_price_100g_usd": 5.29,
    "count_94plus": 4,
    "share_94plus": 0.3636,
    "count_95plus": 0,
    "share_95plus": 0.0,
    "rating_band": "93.00-93.49",
    "rating_band_order": 3,
    "map_note": "Plot at country centroid",
    "label_priority": 0
  },
  {
    "origin_country_norm": "Costa Rica",
    "origin_country_cn": "哥斯达黎加",
    "origin_display_cn": "哥斯达黎加",
    "lat": 9.7489,
    "lon": -83.7534,
    "sample_size": 46,
    "avg_rating": 92.91,
    "median_rating": 93.0,
    "median_price_100g_usd": 5.96,
    "count_94plus": 15,
    "share_94plus": 0.3261,
    "count_95plus": 3,
    "share_95plus": 0.0652,
    "rating_band": "92.50-92.99",
    "rating_band_order": 2,
    "map_note": "Plot at country centroid",
    "label_priority": 0
  },
  {
    "origin_country_norm": "Indonesia",
    "origin_country_cn": "印度尼西亚",
    "origin_display_cn": "印度尼西亚",
    "lat": -0.7893,
    "lon": 113.9213,
    "sample_size": 28,
    "avg_rating": 92.82,
    "median_rating": 93.0,
    "median_price_100g_usd": 5.73,
    "count_94plus": 11,
    "share_94plus": 0.3929,
    "count_95plus": 1,
    "share_95plus": 0.0357,
    "rating_band": "92.50-92.99",
    "rating_band_order": 2,
    "map_note": "Plot at country centroid",
    "label_priority": 0
  },
  {
    "origin_country_norm": "Democratic Republic Of The Congo",
    "origin_country_cn": "刚果（金）",
    "origin_display_cn": "刚果（金）",
    "lat": -4.0383,
    "lon": 21.7587,
    "sample_size": 14,
    "avg_rating": 92.71,
    "median_rating": 93.0,
    "median_price_100g_usd": 5.51,
    "count_94plus": 3,
    "share_94plus": 0.2143,
    "count_95plus": 0,
    "share_95plus": 0.0,
    "rating_band": "92.50-92.99",
    "rating_band_order": 2,
    "map_note": "Plot at country centroid",
    "label_priority": 0
  },
  {
    "origin_country_norm": "El Salvador",
    "origin_country_cn": "萨尔瓦多",
    "origin_display_cn": "萨尔瓦多",
    "lat": 13.7942,
    "lon": -88.8965,
    "sample_size": 14,
    "avg_rating": 92.64,
    "median_rating": 92.0,
    "median_price_100g_usd": 7.67,
    "count_94plus": 5,
    "share_94plus": 0.3571,
    "count_95plus": 2,
    "share_95plus": 0.1429,
    "rating_band": "92.50-92.99",
    "rating_band_order": 2,
    "map_note": "Plot at country centroid",
    "label_priority": 0
  },
  {
    "origin_country_norm": "Burundi",
    "origin_country_cn": "布隆迪",
    "origin_display_cn": "布隆迪",
    "lat": -3.3731,
    "lon": 29.9189,
    "sample_size": 12,
    "avg_rating": 92.5,
    "median_rating": 92.0,
    "median_price_100g_usd": 6.17,
    "count_94plus": 1,
    "share_94plus": 0.0833,
    "count_95plus": 0,
    "share_95plus": 0.0,
    "rating_band": "92.50-92.99",
    "rating_band_order": 2,
    "map_note": "Plot at country centroid",
    "label_priority": 0
  },
  {
    "origin_country_norm": "Peru",
    "origin_country_cn": "秘鲁",
    "origin_display_cn": "秘鲁",
    "lat": -9.19,
    "lon": -75.0152,
    "sample_size": 13,
    "avg_rating": 92.31,
    "median_rating": 93.0,
    "median_price_100g_usd": 5.28,
    "count_94plus": 1,
    "share_94plus": 0.0769,
    "count_95plus": 0,
    "share_95plus": 0.0,
    "rating_band": "92.00-92.49",
    "rating_band_order": 1,
    "map_note": "Plot at country centroid",
    "label_priority": 0
  },
  {
    "origin_country_norm": "Guatemala",
    "origin_country_cn": "危地马拉",
    "origin_display_cn": "危地马拉",
    "lat": 15.7835,
    "lon": -90.2308,
    "sample_size": 96,
    "avg_rating": 92.3,
    "median_rating": 93.0,
    "median_price_100g_usd": 5.0,
    "count_94plus": 18,
    "share_94plus": 0.1875,
    "count_95plus": 3,
    "share_95plus": 0.0312,
    "rating_band": "92.00-92.49",
    "rating_band_order": 1,
    "map_note": "Plot at country centroid",
    "label_priority": 1
  },
  {
    "origin_country_norm": "Rwanda",
    "origin_country_cn": "卢旺达",
    "origin_display_cn": "卢旺达",
    "lat": -1.9403,
    "lon": 29.8739,
    "sample_size": 12,
    "avg_rating": 92.25,
    "median_rating": 92.0,
    "median_price_100g_usd": 4.99,
    "count_94plus": 1,
    "share_94plus": 0.0833,
    "count_95plus": 0,
    "share_95plus": 0.0,
    "rating_band": "92.00-92.49",
    "rating_band_order": 1,
    "map_note": "Plot at country centroid",
    "label_priority": 0
  },
  {
    "origin_country_norm": "Brazil",
    "origin_country_cn": "巴西",
    "origin_display_cn": "巴西",
    "lat": -14.235,
    "lon": -51.9253,
    "sample_size": 15,
    "avg_rating": 92.2,
    "median_rating": 92.0,
    "median_price_100g_usd": 5.28,
    "count_94plus": 3,
    "share_94plus": 0.2,
    "count_95plus": 0,
    "share_95plus": 0.0,
    "rating_band": "92.00-92.49",
    "rating_band_order": 1,
    "map_note": "Plot at country centroid",
    "label_priority": 0
  },
  {
    "origin_country_norm": "Mexico",
    "origin_country_cn": "墨西哥",
    "origin_display_cn": "墨西哥",
    "lat": 23.6345,
    "lon": -102.5528,
    "sample_size": 11,
    "avg_rating": 92.0,
    "median_rating": 92.0,
    "median_price_100g_usd": 5.29,
    "count_94plus": 0,
    "share_94plus": 0.0,
    "count_95plus": 0,
    "share_95plus": 0.0,
    "rating_band": "92.00-92.49",
    "rating_band_order": 1,
    "map_note": "Plot at country centroid",
    "label_priority": 0
  }
]
